pipo_reg.v
// This is similar to a parameterized d flip flop, with "width" no: of bits

module pipo_reg #(parameter width = 8)(
    input wire clk,
    input wire load, //similar to enable
    input wire [(width - 1):0]data_in, //similar to d in dflipflop
    input wire reset,
    output reg [(width - 1):0]data_out //similar to q in dflipflop
);

always @ (posedge clk or posedge reset) begin
    if(reset) begin
      data_out <= {width{1'b0}}; // replication operator
    end

    else if(load) begin
      data_out <= data_in;
    end
end

endmodule

tb.v
`timescale 1ns/1ps
`include "pipo_reg.v"

module tb();

    localparam width = 8;
    localparam clk_period = 5;

    reg clk;
    reg load;
    reg [(width - 1):0]data_in; //similar to d in dflipflop
    reg reset;
    wire [(width - 1):0]data_out;

    pipo_reg #(.width(width)) uut (.clk(clk), .load(load), .data_in(data_in), .reset(reset), .data_out(data_out));

initial begin
    $dumpfile("dump.vcd");
    $dumpvars(0,tb);
end

always #clk_period begin
    clk <= ~(clk);
end

initial begin
  clk = 0; reset = 1; load = 0; data_in = 0;

  #20 reset = 0;

  #10 data_in = 8'b10101010; load = 1;
  #10 load = 0;

  #20 data_in = 8'b01010101; load = 1;
  #10 load = 0;

  #20 data_in = 8'b11111111;

  #50 $finish;
end

initial begin
  $monitor("reset = %b, clk = %b, load = %b, data_in = %b, data_out = %b", reset, clk, load, data_in, data_out);
end

endmodule

dump.vcd
$date
	Sun Jun 01 22:39:54 2025
$end
$version
	Icarus Verilog
$end
$timescale
	1ps
$end
$scope module tb $end
$var wire 8 ! data_out [7:0] $end
$var reg 1 " clk $end
$var reg 8 # data_in [7:0] $end
$var reg 1 $ load $end
$var reg 1 % reset $end
$scope module uut $end
$var wire 1 " clk $end
$var wire 8 & data_in [7:0] $end
$var wire 1 $ load $end
$var wire 1 % reset $end
$var reg 8 ' data_out [7:0] $end
$upscope $end
$upscope $end
$enddefinitions $end
#0
$dumpvars
b0 '
b0 &
1%
0$
b0 #
0"
b0 !
$end
#5000
1"
#10000
0"
#15000
1"
#20000
0"
0%
#25000
1"
#30000
0"
1$
b10101010 #
b10101010 &
#35000
b10101010 !
b10101010 '
1"
#40000
0"
0$
#45000
1"
#50000
0"
#55000
1"
#60000
0"
1$
b1010101 #
b1010101 &
#65000
b1010101 !
b1010101 '
1"
#70000
0"
0$
#75000
1"
#80000
0"
#85000
1"
#90000
0"
b11111111 #
b11111111 &
