Testspace/test1.v
module testnotGate(
    input wire a,
    output wire nota
);

    assign nota = ~a;

endmodule

Testspace/test_tb.v
`timescale 1ns/1ps
`include "test1.v"

module test_tb();

    reg a;
    wire nota;

    testnotGate uut(.a(a), .nota(nota));

    initial begin
      
      a = 0;
      $dumpfile("dump.vcd");
      $dumpvars(0, test_tb);

      #10; a = 1;
      #10; a = 0;
      #10; a = 1;
      #10; a = 1;
      #10; a = 0;
      #10; a = 1;
      #10; a = 1;
      #10; a = 0;
      #10; a = 1;
      #10; a = 1;
      #10; a = 0;
      #10; a = 1;

    end

    initial begin
      $monitor("a = %b, nota = %b", a, nota);
    end

endmodule

Testspace/dump.vcd
$date
	Fri May 23 01:24:41 2025
$end
$version
	Icarus Verilog
$end
$timescale
	1ps
$end
$scope module test_tb $end
$var wire 1 ! nota $end
$var reg 1 " a $end
$scope module uut $end
$var wire 1 " a $end
$var wire 1 ! nota $end
$upscope $end
$upscope $end
$enddefinitions $end
#0
$dumpvars
0"
1!
$end
#10000
0!
1"
#20000
1!
0"
#30000
0!
1"
#50000
1!
0"
#60000
0!
1"
#80000
1!
0"
#90000
0!
1"
#110000
1!
0"
#120000
0!
1"
